{
    "id": "ywg",
    "name": "James Armstrong Richardson International Airport",
    "city": "Winnipeg",
    "state": "Manitoba",
    "stateShort": "MB",
    "country": "Canada",
    "description": "With a few exceptions, airport codes starting with ‘*Y*’ designate Canadian airports. James Armstrong Richardson International honors the Canadian aviator, but its airport code honors its home in *W*innipe*g*.",
    "imageCredit": "AJ Batac",
    "imageCreditLink": "https://www.flickr.com/photos/ajbatac/"
}